thickbrick/__init__.py
thickbrick/_statisticaldistances.py
thickbrick/_thickbrick.py
thickbrick/KernelRegression/_NW_kerreg_1d.py
thickbrick/KernelRegression/__init__.py
thickbrick/KernelRegression/_onedim.py
thickbrick-0.1.1.dist-info/LICENSE
thickbrick-0.1.1.dist-info/METADATA
thickbrick-0.1.1.dist-info/WHEEL
thickbrick-0.1.1.dist-info/top_level.txt
thickbrick-0.1.1.dist-info/RECORD
