Metadata-Version: 2.1
Name: thickbrick
Version: 0.1.1
Summary: A data analysis package
Home-page: https://prasanthcakewalk.gitlab.io/thickbrick
Author: Prasanth Shyamsundar
Author-email: prasanth.s.cmi@gmail.com
License: MIT
Keywords: thick brick taab autocategorizer
Platform: any
Classifier: Programming Language :: Python :: 3
Classifier: License :: OSI Approved :: MIT License
Classifier: Operating System :: OS Independent
Classifier: Development Status :: 3 - Alpha
Requires-Python: >=3.6
Requires-Dist: numpy
